pytiff/__init__.py
pytiff/_pytiff.cpython-39-x86_64-linux-gnu.so
pytiff/utils.py
pytiff/_version/__init__.py
pytiff.libs/libjbig-2504a0c3.so.2.1
pytiff.libs/libjpeg-e87d2658.so.62.2.0
pytiff.libs/libtiff-70e1437f.so.5.3.0
pytiff-0.8.4.dist-info/METADATA
pytiff-0.8.4.dist-info/WHEEL
pytiff-0.8.4.dist-info/top_level.txt
pytiff-0.8.4.dist-info/RECORD
pytiff-0.8.4.dist-info/licenses/LICENSE
pytiff-0.8.4.dist-info/sboms/auditwheel.cdx.json
